syntools/__init__.py
syntools/_version.py
syntools/cli.py
syntools/commands/__init__.py
syntools/commands/compare/__init__.py
syntools/commands/compare/cli.py
syntools/commands/compare/compare.py
syntools/commands/copy/__init__.py
syntools/commands/copy/cli.py
syntools/commands/copy/copy.py
syntools/commands/download/__init__.py
syntools/commands/download/cli.py
syntools/commands/download/download.py
syntools/commands/find_id/__init__.py
syntools/commands/find_id/cli.py
syntools/commands/find_id/find_id.py
syntools/commands/invite_to_team/__init__.py
syntools/commands/invite_to_team/cli.py
syntools/commands/invite_to_team/invite_to_team.py
syntools/commands/list/__init__.py
syntools/commands/list/cli.py
syntools/commands/list/list.py
syntools/commands/move/__init__.py
syntools/commands/move/cli.py
syntools/commands/move/move.py
syntools/commands/sync/__init__.py
syntools/commands/sync/cli.py
syntools/commands/sync/sync.py
syntools/core/__init__.py
syntools/core/entity_bundle_wrapper.py
syntools/core/env.py
syntools/core/exceptions.py
syntools/core/logging.py
syntools/core/resumable_queue.py
syntools/core/synapse_item.py
syntools/core/throughput_timer.py
syntools/core/utils.py
syntools-0.0.7.dist-info/LICENSE
syntools-0.0.7.dist-info/METADATA
syntools-0.0.7.dist-info/NOTICE
syntools-0.0.7.dist-info/WHEEL
syntools-0.0.7.dist-info/entry_points.txt
syntools-0.0.7.dist-info/top_level.txt
syntools-0.0.7.dist-info/RECORD
