Metadata-Version: 2.1
Name: syntools
Version: 0.0.7
Summary: Utilities for using Synapse.
Home-page: https://github.com/ki-tools/syntools-py
License: Apache2
Classifier: Programming Language :: Python :: 3.10
Classifier: Programming Language :: Python :: 3.11
Classifier: License :: OSI Approved :: Apache Software License
Classifier: Operating System :: OS Independent
License-File: LICENSE
License-File: NOTICE
Requires-Dist: synapseclient <3.0.0,>=2.3.1
Requires-Dist: synapsis >=0.0.7
